scrapyz/core.py
scrapyz/pipelines.py
scrapyz/settings.py
scrapyz/util.py
scrapyz/__init__.py
scrapyz/examples/reddit_spider.py
scrapyz/examples/__init__.py
scrapyz/test/spiders.py
scrapyz/test/test_generic_spider.py
scrapyz/test/util.py
scrapyz/test/__init__.py
scrapyz-0.3.3.dist-info/DESCRIPTION.rst
scrapyz-0.3.3.dist-info/METADATA
scrapyz-0.3.3.dist-info/metadata.json
scrapyz-0.3.3.dist-info/RECORD
scrapyz-0.3.3.dist-info/top_level.txt
scrapyz-0.3.3.dist-info/WHEEL
